cohere_sagemaker/__init__.py
cohere_sagemaker/classification.py
cohere_sagemaker/client.py
cohere_sagemaker/embeddings.py
cohere_sagemaker/error.py
cohere_sagemaker/generation.py
cohere_sagemaker/rerank.py
cohere_sagemaker/response.py
cohere_sagemaker/summary.py
cohere_sagemaker-0.7.2.dist-info/LICENSE
cohere_sagemaker-0.7.2.dist-info/METADATA
cohere_sagemaker-0.7.2.dist-info/WHEEL
cohere_sagemaker-0.7.2.dist-info/top_level.txt
cohere_sagemaker-0.7.2.dist-info/RECORD
