Metadata-Version: 2.1
Name: cohere-sagemaker
Version: 0.7.2
Summary: A Python library for the Cohere endpoints in AWS Sagemaker
Home-page: https://github.com/cohere-ai/cohere-sagemaker
Author: Cohere
Author-email: support@cohere.ai
Classifier: Programming Language :: Python :: 3
Classifier: License :: OSI Approved :: MIT License
Classifier: Operating System :: OS Independent
Requires-Python: >=3.6
License-File: LICENSE
Requires-Dist: boto3
Requires-Dist: sagemaker
